django_filepond_form_widget/__init__.py
django_filepond_form_widget/widgets.py
django_filepond_form_widget/static/django_filepond_form_widget/css/filepond-plugin-image-preview.min.css
django_filepond_form_widget/static/django_filepond_form_widget/css/filepond.min.css
django_filepond_form_widget/static/django_filepond_form_widget/js/filepond-plugin-file-validate-size.min.js
django_filepond_form_widget/static/django_filepond_form_widget/js/filepond-plugin-file-validate-type.min.js
django_filepond_form_widget/static/django_filepond_form_widget/js/filepond-plugin-image-preview.min.js
django_filepond_form_widget/static/django_filepond_form_widget/js/filepond-plugin-image-resize.min.js
django_filepond_form_widget/static/django_filepond_form_widget/js/filepond.min.js
django_filepond_form_widget/static/django_filepond_form_widget/js/init_filepond.js
django_filepond_form_widget/static/django_filepond_form_widget/locale/am-et.js
django_filepond_form_widget/static/django_filepond_form_widget/locale/ar-ar.js
django_filepond_form_widget/static/django_filepond_form_widget/locale/az-az.js
django_filepond_form_widget/static/django_filepond_form_widget/locale/ca-ca.js
django_filepond_form_widget/static/django_filepond_form_widget/locale/cs-cz.js
django_filepond_form_widget/static/django_filepond_form_widget/locale/da-dk.js
django_filepond_form_widget/static/django_filepond_form_widget/locale/de-de.js
django_filepond_form_widget/static/django_filepond_form_widget/locale/el-el.js
django_filepond_form_widget/static/django_filepond_form_widget/locale/en-en.js
django_filepond_form_widget/static/django_filepond_form_widget/locale/es-es.js
django_filepond_form_widget/static/django_filepond_form_widget/locale/et-ee.js
django_filepond_form_widget/static/django_filepond_form_widget/locale/fa_ir.js
django_filepond_form_widget/static/django_filepond_form_widget/locale/fi-fi.js
django_filepond_form_widget/static/django_filepond_form_widget/locale/fr-fr.js
django_filepond_form_widget-0.3.0.dist-info/METADATA
django_filepond_form_widget-0.3.0.dist-info/WHEEL
django_filepond_form_widget-0.3.0.dist-info/licenses/LICENSE
django_filepond_form_widget-0.3.0.dist-info/RECORD
