Metadata-Version: 2.4
Name: django-filepond-form-widget
Version: 0.3.0
Summary: A Django form widget using FilePond with image preview support
Author-email: Krystof Beuermann <krystof+django@blackbox.ms>
License: MIT License
License-File: LICENSE
Keywords: django,filepond,widget
Requires-Python: >=3.8
Requires-Dist: django>=4.2
